{
  "variants": {
    "age=0": {
      "model": "projectredxt:block/ruby_stage0"
    },
    "age=1": {
      "model": "projectredxt:block/ruby_stage1"
    },
    "age=2": {
      "model": "projectredxt:block/ruby_stage2"
    },
    "age=3": {
      "model": "projectredxt:block/ruby_stage3"
    },
    "age=4": {
      "model": "projectredxt:block/ruby_stage4"
    },
    "age=5": {
      "model": "projectredxt:block/ruby_stage5"
    },
    "age=6": {
      "model": "projectredxt:block/ruby_stage6"
    },
    "age=7": {
      "model": "projectredxt:block/ruby_stage7"
    }
  }
}